{
  "image_path": "backend/resources/greenMaps/PresidioGC/Hole_5/Hole_5_contour.png",
  "image_w_px": 1206,
  "image_h_px": 1303,
  "green_width_ft": 78.35224823867375,
  "green_height_ft": 118.93698326767894,
  "contour_interval_ft": 0.25,
  "contours": [
    {
      "k": 0,
      "height_ft": 0.0,
      "points_xz_ft": [
        {
          "x": -0.1699100168967154,
          "z": -49.86541580715474
        },
        {
          "x": -1.2006025309396522,
          "z": -46.58306399619608
        },
        {
          "x": -2.9184233876778705,
          "z": -43.39725194438324
        },
        {
          "x": -5.323372587111385,
          "z": -40.88721820659133
        },
        {
          "x": -8.003173123623013,
          "z": -38.1841049505077
        },
        {
          "x": -11.095250665751815,
          "z": -35.4809916944241
        },
        {
          "x": -13.84376403653297,
          "z": -35.19137241698655
        }
      ]
    },
    {
      "k": 1,
      "height_ft": 0.25,
      "points_xz_ft": [
        {
          "x": 2.9221675252320805,
          "z": -51.60313147177994
        },
        {
          "x": 2.5786033538844397,
          "z": -47.5484615876545
        },
        {
          "x": 1.6853365083805592,
          "z": -44.748808572425055
        },
        {
          "x": -0.30733568543577167,
          "z": -41.46645676146638
        },
        {
          "x": -3.124561890486455,
          "z": -37.89448567307018
        },
        {
          "x": -5.80436242699809,
          "z": -34.129435066382285
        },
        {
          "x": -9.033865637665942,
          "z": -31.040162773715295
        },
        {
          "x": -11.3013891685604,
          "z": -29.01282783165259
        },
        {
          "x": -15.011882219114955,
          "z": -27.468191685319102
        },
        {
          "x": -17.76039558989612,
          "z": -27.564731444464947
        }
      ]
    },
    {
      "k": 2,
      "height_ft": 0.5,
      "points_xz_ft": [
        {
          "x": 10.824143466227905,
          "z": -55.17510256017612
        },
        {
          "x": 7.869491592638166,
          "z": -52.278909785800835
        },
        {
          "x": 5.739393730282764,
          "z": -48.32077966082126
        },
        {
          "x": 3.678008702196905,
          "z": -43.39725194438324
        },
        {
          "x": 2.1663263482672708,
          "z": -39.82528085598704
        },
        {
          "x": 0.8607824971462215,
          "z": -35.57753145356994
        },
        {
          "x": -1.2006025309396522,
          "z": -33.067497715778
        },
        {
          "x": -3.261987559025511,
          "z": -29.205907349944273
        },
        {
          "x": -4.22396723879892,
          "z": -25.73047602069392
        },
        {
          "x": -6.560203603962906,
          "z": -23.60660131948536
        },
        {
          "x": -9.583568311822175,
          "z": -20.806948304255908
        },
        {
          "x": -13.22534852810721,
          "z": -18.586533843901513
        },
        {
          "x": -16.5235645730446,
          "z": -15.014562755505311
        },
        {
          "x": -18.859800938208576,
          "z": -12.021830221984171
        },
        {
          "x": -20.98989880056397,
          "z": -6.905222987254471
        },
        {
          "x": -23.944550674153717,
          "z": -1.2093771976497176
        }
      ]
    },
    {
      "k": 3,
      "height_ft": 0.75,
      "points_xz_ft": [
        {
          "x": 16.870872881946454,
          "z": -55.368182078467825
        },
        {
          "x": 14.397210848243413,
          "z": -51.216972435196546
        },
        {
          "x": 12.060974483079427,
          "z": -49.093097733987996
        },
        {
          "x": 9.518599615106856,
          "z": -46.969223032779446
        },
        {
          "x": 6.838799078595229,
          "z": -44.36264953584169
        },
        {
          "x": 5.189691056126539,
          "z": -40.30797965171625
        },
        {
          "x": 3.8154343707359613,
          "z": -36.446389285882525
        },
        {
          "x": 2.1663263482672708,
          "z": -32.48825916090295
        },
        {
          "x": 0.9294953314157497,
          "z": -28.530129035923377
        },
        {
          "x": -0.3760485197052998,
          "z": -24.861618188381332
        },
        {
          "x": -2.4374335477911737,
          "z": -21.289647099985128
        },
        {
          "x": -4.1552544045293915,
          "z": -17.91075552988061
        },
        {
          "x": -6.835054941041019,
          "z": -15.304182032942837
        },
        {
          "x": -10.820399328673695,
          "z": -11.925290462838328
        },
        {
          "x": -13.294061362376738,
          "z": -8.932557929317179
        },
        {
          "x": -15.905149064618836,
          "z": -5.457126600066816
        },
        {
          "x": -17.691682755626584,
          "z": -2.754013343983214
        },
        {
          "x": -20.37148329213822,
          "z": 1.3006565401422114
        },
        {
          "x": -25.043956022466183,
          "z": 5.0657071468301
        }
      ]
    },
    {
      "k": 4,
      "height_ft": 1.0,
      "points_xz_ft": [
        {
          "x": 20.718791601040074,
          "z": -55.464721837613666
        },
        {
          "x": 19.344534915649497,
          "z": -51.216972435196546
        },
        {
          "x": 16.870872881946454,
          "z": -47.64500134680034
        },
        {
          "x": 13.435231168470004,
          "z": -45.038427849862586
        },
        {
          "x": 10.480579294880265,
          "z": -42.818013389508195
        },
        {
          "x": 7.938204426907694,
          "z": -39.14950254196614
        },
        {
          "x": 6.701373410056172,
          "z": -35.384451935278236
        },
        {
          "x": 4.777414050509369,
          "z": -31.23324229200698
        },
        {
          "x": 3.6092958679273766,
          "z": -29.302447109090124
        },
        {
          "x": 2.5786033538844397,
          "z": -25.537396502402228
        },
        {
          "x": 0.4485054915290379,
          "z": -21.096567581693442
        },
        {
          "x": -1.2693153652091804,
          "z": -17.91075552988061
        },
        {
          "x": -2.7809977191388144,
          "z": -13.952625404901037
        },
        {
          "x": -5.941788095537146,
          "z": -11.056432630525737
        },
        {
          "x": -8.690301466318301,
          "z": -6.712143468962786
        },
        {
          "x": -11.782379008447105,
          "z": -2.560933825691519
        },
        {
          "x": -14.943169384845428,
          "z": 1.0110372627046846
        },
        {
          "x": -18.516236766860935,
          "z": 5.162246905975942
        },
        {
          "x": -25.043956022466183,
          "z": 7.865360162059555
        }
      ]
    },
    {
      "k": 5,
      "height_ft": 1.25,
      "points_xz_ft": [
        {
          "x": 24.017007645977454,
          "z": -54.8854832827386
        },
        {
          "x": 23.329879303282176,
          "z": -50.251574843738126
        },
        {
          "x": 21.33720710946583,
          "z": -46.38998447790438
        },
        {
          "x": 19.20710924711044,
          "z": -42.818013389508195
        },
        {
          "x": 14.53463651678247,
          "z": -40.40451941086209
        },
        {
          "x": 10.755430631958378,
          "z": -37.79794591392434
        },
        {
          "x": 8.07563009544675,
          "z": -33.067497715778
        },
        {
          "x": 6.357809238708532,
          "z": -29.01282783165259
        },
        {
          "x": 3.8154343707359613,
          "z": -23.992760356068743
        },
        {
          "x": 1.547910839841503,
          "z": -20.034630231089157
        },
        {
          "x": 0.4485054915290379,
          "z": -16.65573866098465
        },
        {
          "x": -0.8570383595920116,
          "z": -13.952625404901037
        },
        {
          "x": -3.124561890486455,
          "z": -10.28411455735899
        },
        {
          "x": -5.048521250033265,
          "z": -7.001762746400313
        },
        {
          "x": -7.659608952275364,
          "z": -2.754013343983214
        },
        {
          "x": -10.476835157326054,
          "z": 0.04563967124625212
        },
        {
          "x": -12.675645853950977,
          "z": 3.424531241350761
        },
        {
          "x": -15.49287205900166,
          "z": 6.417263774871901
        },
        {
          "x": -19.065939441017168,
          "z": 9.023837271809672
        },
        {
          "x": -25.318807359544294,
          "z": 11.340791491309917
        }
      ]
    },
    {
      "k": 6,
      "height_ft": 1.5,
      "points_xz_ft": [
        {
          "x": 26.765521016758612,
          "z": -51.79621099007162
        },
        {
          "x": 25.803541336985216,
          "z": -47.74154110594619
        },
        {
          "x": 24.22314614878604,
          "z": -44.45918929498753
        },
        {
          "x": 21.131068606657244,
          "z": -40.21143989257041
        },
        {
          "x": 17.832852561719864,
          "z": -37.70140615477849
        },
        {
          "x": 14.46592368251294,
          "z": -35.384451935278236
        },
        {
          "x": 11.648697477462258,
          "z": -33.74327602979892
        },
        {
          "x": 8.762758438142047,
          "z": -29.688606145673496
        },
        {
          "x": 7.044937581403813,
          "z": -25.054697706673018
        },
        {
          "x": 4.639988381970314,
          "z": -19.938090471943315
        },
        {
          "x": 2.784741856693024,
          "z": -16.55919890183881
        },
        {
          "x": 1.2730595027633904,
          "z": -12.794148295150908
        },
        {
          "x": -0.8570383595920116,
          "z": -9.4152567250464
        },
        {
          "x": -3.055849056216927,
          "z": -5.16750732262929
        },
        {
          "x": -5.254659752841857,
          "z": -1.9816952708164657
        },
        {
          "x": -7.865747455083956,
          "z": 1.590275817579738
        },
        {
          "x": -10.408122323056526,
          "z": 5.0657071468301
        },
        {
          "x": -13.019210025298618,
          "z": 8.154979439497081
        },
        {
          "x": -16.5235645730446,
          "z": 10.761552936434853
        },
        {
          "x": -20.852473132024915,
          "z": 13.078507155935098
        },
        {
          "x": -24.83781751965759,
          "z": 13.56120595166431
        }
      ]
    },
    {
      "k": 7,
      "height_ft": 1.75,
      "points_xz_ft": [
        {
          "x": 28.345916204957774,
          "z": -47.83808086509205
        },
        {
          "x": 26.0096798397938,
          "z": -42.4318543529248
        },
        {
          "x": 24.29185898305557,
          "z": -39.05296278282028
        },
        {
          "x": 22.23047395496971,
          "z": -35.19137241698655
        },
        {
          "x": 19.413247749919027,
          "z": -33.16403747492386
        },
        {
          "x": 15.565329030825406,
          "z": -31.7159410877362
        },
        {
          "x": 11.511271808923201,
          "z": -29.01282783165259
        },
        {
          "x": 8.96889694095063,
          "z": -25.537396502402228
        },
        {
          "x": 7.044937581403813,
          "z": -21.096567581693442
        },
        {
          "x": 4.777414050509369,
          "z": -16.75227842013049
        },
        {
          "x": 2.647316188153968,
          "z": -12.601068776859224
        },
        {
          "x": 0.6546439943376371,
          "z": -8.642938651879652
        },
        {
          "x": -1.6128795365568211,
          "z": -4.298649490316699
        },
        {
          "x": -3.674264564642695,
          "z": -1.1128374385038753
        },
        {
          "x": -5.460798255650441,
          "z": 1.3971962992880536
        },
        {
          "x": -7.659608952275364,
          "z": 4.389928832809193
        },
        {
          "x": -10.201983820247934,
          "z": 7.382661366330344
        },
        {
          "x": -12.95049719102909,
          "z": 9.699615585830578
        },
        {
          "x": -15.973861898888366,
          "z": 12.981967396789255
        },
        {
          "x": -19.95920628652104,
          "z": 15.105842097997805
        },
        {
          "x": -22.91385816011078,
          "z": 15.395461375435332
        },
        {
          "x": -24.219402011231832,
          "z": 20.222449332727503
        }
      ]
    },
    {
      "k": 8,
      "height_ft": 2.0,
      "points_xz_ft": [
        {
          "x": 28.826906044844485,
          "z": -43.39725194438324
        },
        {
          "x": 26.971659519567197,
          "z": -39.535661578549515
        },
        {
          "x": 25.940967005524275,
          "z": -35.96369049015331
        },
        {
          "x": 23.536017806090758,
          "z": -32.48825916090295
        },
        {
          "x": 20.650078766770548,
          "z": -29.59206638652765
        },
        {
          "x": 17.14572421902457,
          "z": -27.468191685319102
        },
        {
          "x": 13.984933842626244,
          "z": -25.923555538985607
        },
        {
          "x": 11.511271808923201,
          "z": -22.930823005464468
        },
        {
          "x": 8.694045603872517,
          "z": -18.39345432560983
        },
        {
          "x": 6.08295790163042,
          "z": -14.724943478067784
        },
        {
          "x": 3.4718701993883205,
          "z": -11.442591667109108
        },
        {
          "x": 1.6853365083805592,
          "z": -7.870620578712903
        },
        {
          "x": -0.3760485197052998,
          "z": -3.526331417149952
        },
        {
          "x": -2.9871362219473987,
          "z": 0.23871918953793655
        },
        {
          "x": -5.185946918572329,
          "z": 3.8106902779341403
        },
        {
          "x": -7.797034620814427,
          "z": 7.1895818480386495
        },
        {
          "x": -10.682973660134639,
          "z": 9.892695104122263
        },
        {
          "x": -13.637625533724378,
          "z": 13.56120595166431
        },
        {
          "x": -17.41683141854847,
          "z": 16.457398726039607
        },
        {
          "x": -22.089304148876437,
          "z": 18.484733668102326
        },
        {
          "x": -23.25742233145843,
          "z": 24.952897530873816
        }
      ]
    },
    {
      "k": 9,
      "height_ft": 2.25,
      "points_xz_ft": [
        {
          "x": 29.101757381922596,
          "z": -39.05296278282028
        },
        {
          "x": 27.315223690914852,
          "z": -35.19137241698655
        },
        {
          "x": 24.704135988672753,
          "z": -31.040162773715295
        },
        {
          "x": 22.57403812631735,
          "z": -27.178572407881568
        },
        {
          "x": 19.344534915649497,
          "z": -23.51006156033952
        },
        {
          "x": 15.77146753363399,
          "z": -21.868885654860183
        },
        {
          "x": 12.748102825774723,
          "z": -19.26231215792242
        },
        {
          "x": 10.892856300497433,
          "z": -15.690341069526216
        },
        {
          "x": 8.694045603872517,
          "z": -13.373386850025973
        },
        {
          "x": 5.12097822185701,
          "z": -10.091035039067306
        },
        {
          "x": 3.197018862310193,
          "z": -6.229444673233565
        },
        {
          "x": 0.7233568286071652,
          "z": -1.8851555116706233
        },
        {
          "x": -2.231295044982589,
          "z": 1.3006565401422114
        },
        {
          "x": -3.9491159017208073,
          "z": 5.355326424267626
        },
        {
          "x": -6.42277793542385,
          "z": 7.865360162059555
        },
        {
          "x": -9.583568311822175,
          "z": 11.244251732164074
        },
        {
          "x": -12.469507351142394,
          "z": 14.91276257970612
        },
        {
          "x": -16.45485173877507,
          "z": 18.098574631518954
        },
        {
          "x": -19.40950361236481,
          "z": 20.02936981443582
        },
        {
          "x": -21.40217580618115,
          "z": 21.574005960769316
        },
        {
          "x": -22.364155485954555,
          "z": 28.13870958268665
        }
      ]
    },
    {
      "k": 10,
      "height_ft": 2.5,
      "points_xz_ft": [
        {
          "x": 28.07106486787966,
          "z": -31.52286156944452
        },
        {
          "x": 25.52868999990709,
          "z": -27.27511216702741
        },
        {
          "x": 23.123740800473577,
          "z": -23.413521801193678
        },
        {
          "x": 20.718791601040074,
          "z": -20.51732902681838
        },
        {
          "x": 17.351862721833154,
          "z": -17.331516975005545
        },
        {
          "x": 14.053646676895772,
          "z": -13.856085645755194
        },
        {
          "x": 10.27444079207168,
          "z": -10.573733834796517
        },
        {
          "x": 7.18236324994287,
          "z": -7.581001301275377
        },
        {
          "x": 4.4338498791617145,
          "z": -4.202109731170857
        },
        {
          "x": 1.8914750111891583,
          "z": -1.0162976793580332
        },
        {
          "x": -0.8570383595920116,
          "z": 3.2314517230590765
        },
        {
          "x": -3.742977398912223,
          "z": 7.672280643767871
        },
        {
          "x": -6.697629272501962,
          "z": 11.244251732164074
        },
        {
          "x": -9.583568311822175,
          "z": 15.298921616289489
        },
        {
          "x": -13.56891269945485,
          "z": 18.1951143906648
        },
        {
          "x": -17.279405750009413,
          "z": 21.091307165040085
        },
        {
          "x": -20.302770457868682,
          "z": 24.084039698561234
        },
        {
          "x": -20.783760297755386,
          "z": 28.52486861927002
        },
        {
          "x": -20.852473132024915,
          "z": 33.35185657656219
        }
      ]
    },
    {
      "k": 11,
      "height_ft": 2.75,
      "points_xz_ft": [
        {
          "x": 25.18512582855945,
          "z": -22.158504932297717
        },
        {
          "x": 22.299186789239236,
          "z": -19.358851917068264
        },
        {
          "x": 20.856217269579133,
          "z": -15.497261551234523
        },
        {
          "x": 17.901565395989394,
          "z": -12.601068776859224
        },
        {
          "x": 14.809487853860581,
          "z": -9.994495279921454
        },
        {
          "x": 12.404538654427068,
          "z": -7.194842264691998
        },
        {
          "x": 9.106322609489688,
          "z": -4.4917290086083845
        },
        {
          "x": 6.220383570169475,
          "z": -1.7886157525247708
        },
        {
          "x": 3.197018862310193,
          "z": 1.204116780996369
        },
        {
          "x": 1.066920999954806,
          "z": 4.583008351100878
        },
        {
          "x": -1.7503052050958774,
          "z": 8.830757753517988
        },
        {
          "x": -4.430105741607512,
          "z": 11.726950527893285
        },
        {
          "x": -7.041193443849603,
          "z": 14.91276257970612
        },
        {
          "x": -9.99584531743935,
          "z": 18.1951143906648
        },
        {
          "x": -13.912476870802498,
          "z": 21.380926442477612
        },
        {
          "x": -17.073267247200828,
          "z": 24.37365897599876
        },
        {
          "x": -19.065939441017168,
          "z": 28.235249341832493
        },
        {
          "x": -19.478216446634338,
          "z": 32.676078262541296
        },
        {
          "x": -19.272077943825753,
          "z": 36.827287905812554
        }
      ]
    },
    {
      "k": 12,
      "height_ft": 3.0,
      "points_xz_ft": [
        {
          "x": 24.29185898305557,
          "z": -17.814215770734766
        },
        {
          "x": 22.23047395496971,
          "z": -14.724943478067784
        },
        {
          "x": 19.413247749919027,
          "z": -10.573733834796517
        },
        {
          "x": 17.07701138475504,
          "z": -6.905222987254471
        },
        {
          "x": 13.778795339817645,
          "z": -3.815950694587489
        },
        {
          "x": 9.930876620724039,
          "z": -0.9197579202121908
        },
        {
          "x": 6.563947741517116,
          "z": 1.204116780996369
        },
        {
          "x": 3.6092958679273766,
          "z": 4.196849314517509
        },
        {
          "x": 0.9982081656852778,
          "z": 8.05843968035124
        },
        {
          "x": -1.8190180393654056,
          "z": 11.43733125045576
        },
        {
          "x": -4.017828735990336,
          "z": 14.526603543122741
        },
        {
          "x": -7.178619112388667,
          "z": 17.712415594935564
        },
        {
          "x": -9.99584531743935,
          "z": 20.608608369310875
        },
        {
          "x": -12.332081682603329,
          "z": 23.987499939415393
        },
        {
          "x": -14.53089237922826,
          "z": 26.690613195498997
        },
        {
          "x": -16.45485173877507,
          "z": 28.13870958268665
        },
        {
          "x": -17.966534092704702,
          "z": 32.579538503395455
        },
        {
          "x": -18.172672595513287,
          "z": 37.40652646068761
        },
        {
          "x": -17.691682755626584,
          "z": 40.39925899420876
        }
      ]
    },
    {
      "k": 13,
      "height_ft": 3.25,
      "points_xz_ft": [
        {
          "x": 24.429284651594624,
          "z": -14.724943478067784
        },
        {
          "x": 22.780176629125936,
          "z": -12.40798925856754
        },
        {
          "x": 20.99364293811819,
          "z": -8.642938651879652
        },
        {
          "x": 19.481960584188556,
          "z": -5.264047081775132
        },
        {
          "x": 16.939585716215984,
          "z": -2.3678543073998344
        },
        {
          "x": 14.1223595111653,
          "z": -0.24397960619128492
        },
        {
          "x": 11.167707637575546,
          "z": 1.493736058433896
        },
        {
          "x": 8.213055763985807,
          "z": 3.9072300370799824
        },
        {
          "x": 6.014245067360891,
          "z": 6.417263774871901
        },
        {
          "x": 3.884147205005489,
          "z": 8.05843968035124
        },
        {
          "x": 1.8914750111891583,
          "z": 11.340791491309917
        },
        {
          "x": -1.2693153652091804,
          "z": 14.719683061414436
        },
        {
          "x": -3.9491159017208073,
          "z": 18.1951143906648
        },
        {
          "x": -6.14792659834573,
          "z": 20.51206861016503
        },
        {
          "x": -8.278024460701124,
          "z": 22.442863793081898
        },
        {
          "x": -9.99584531743935,
          "z": 26.49753367720731
        },
        {
          "x": -12.263368848333801,
          "z": 29.104107174145092
        },
        {
          "x": -14.53089237922826,
          "z": 30.64874332047857
        },
        {
          "x": -16.11128756742742,
          "z": 33.834555372291405
        },
        {
          "x": -16.86712874439224,
          "z": 37.59960597897929
        },
        {
          "x": -16.5235645730446,
          "z": 42.136974658833935
        }
      ]
    },
    {
      "k": 14,
      "height_ft": 3.5,
      "points_xz_ft": [
        {
          "x": 24.29185898305557,
          "z": -11.925290462838328
        },
        {
          "x": 22.642750960586877,
          "z": -9.4152567250464
        },
        {
          "x": 21.474632778004885,
          "z": -5.16750732262929
        },
        {
          "x": 20.237801761153364,
          "z": -1.1128374385038753
        },
        {
          "x": 16.7334472134074,
          "z": 1.7833553358714225
        },
        {
          "x": 12.954241328583308,
          "z": 4.389928832809193
        },
        {
          "x": 9.587312449376384,
          "z": 7.4792011254761865
        },
        {
          "x": 6.08295790163042,
          "z": 10.375393899851485
        },
        {
          "x": 2.9908803595016087,
          "z": 13.464666192518466
        },
        {
          "x": 0.10494132018139718,
          "z": 17.133177040060513
        },
        {
          "x": -2.231295044982589,
          "z": 20.41552885101919
        },
        {
          "x": -4.636244244416096,
          "z": 23.697880661977866
        },
        {
          "x": -7.247331946658195,
          "z": 27.849090305249124
        },
        {
          "x": -9.446142643283117,
          "z": 31.421061393645328
        },
        {
          "x": -12.332081682603329,
          "z": 34.89649272289569
        },
        {
          "x": -14.737030882036844,
          "z": 38.951162607021104
        },
        {
          "x": -14.737030882036844,
          "z": 44.64700839662586
        }
      ]
    },
    {
      "k": 15,
      "height_ft": 3.75,
      "points_xz_ft": [
        {
          "x": 24.429284651594624,
          "z": -8.932557929317179
        },
        {
          "x": 23.192453634743117,
          "z": -5.16750732262929
        },
        {
          "x": 22.299186789239236,
          "z": -1.8851555116706233
        },
        {
          "x": 21.2684942751963,
          "z": 1.107577021850527
        },
        {
          "x": 19.20710924711044,
          "z": 4.583008351100878
        },
        {
          "x": 14.53463651678247,
          "z": 8.44459871693462
        },
        {
          "x": 12.404538654427068,
          "z": 9.989234863268106
        },
        {
          "x": 10.27444079207168,
          "z": 11.5338710096016
        },
        {
          "x": 8.07563009544675,
          "z": 13.754285469956002
        },
        {
          "x": 5.327116724665595,
          "z": 16.6504782443313
        },
        {
          "x": 2.784741856693024,
          "z": 19.353591500414904
        },
        {
          "x": 0.17365415445092533,
          "z": 22.249784274790212
        },
        {
          "x": -1.8190180393654056,
          "z": 26.49753367720731
        },
        {
          "x": -3.674264564642695,
          "z": 30.552203561332725
        },
        {
          "x": -6.42277793542385,
          "z": 35.089572241187376
        },
        {
          "x": -9.514855477552645,
          "z": 38.951162607021104
        },
        {
          "x": -11.782379008447105,
          "z": 42.71621321370899
        },
        {
          "x": -12.606933019681449,
          "z": 48.12243972587622
        }
      ]
    },
    {
      "k": 16,
      "height_ft": 4.0,
      "points_xz_ft": [
        {
          "x": 24.566710320133694,
          "z": -4.202109731170857
        },
        {
          "x": 23.398592137551702,
          "z": 0.04563967124625212
        },
        {
          "x": 21.68077128081347,
          "z": 5.644945701705163
        },
        {
          "x": 18.72611940722373,
          "z": 9.409996308393051
        },
        {
          "x": 15.634041865094934,
          "z": 11.726950527893285
        },
        {
          "x": 11.854835980270842,
          "z": 14.719683061414436
        },
        {
          "x": 7.869491592638166,
          "z": 18.77435294553985
        },
        {
          "x": 5.12097822185701,
          "z": 21.380926442477612
        },
        {
          "x": 2.784741856693024,
          "z": 25.1459770491655
        },
        {
          "x": 0.7920696628766933,
          "z": 29.49026621072846
        },
        {
          "x": -1.3380281994787084,
          "z": 32.676078262541296
        },
        {
          "x": -3.6055517303731666,
          "z": 37.79268549727097
        },
        {
          "x": -5.460798255650441,
          "z": 41.65427586310471
        },
        {
          "x": -7.659608952275364,
          "z": 43.77815056431328
        },
        {
          "x": -9.37742980901359,
          "z": 47.25358189356364
        },
        {
          "x": -9.927132483169823,
          "z": 50.53593370452229
        }
      ]
    },
    {
      "k": 17,
      "height_ft": 4.25,
      "points_xz_ft": [
        {
          "x": 24.22314614878604,
          "z": 3.5210710004966033
        },
        {
          "x": 23.055027966204047,
          "z": 7.865360162059555
        },
        {
          "x": 20.787504435309604,
          "z": 11.05117221387239
        },
        {
          "x": 17.695426893180795,
          "z": 13.56120595166431
        },
        {
          "x": 14.672062185321526,
          "z": 16.55393848518546
        },
        {
          "x": 11.648697477462258,
          "z": 19.353591500414904
        },
        {
          "x": 8.831471272411575,
          "z": 22.53940355222774
        },
        {
          "x": 5.945532233091363,
          "z": 25.918295122332257
        },
        {
          "x": 3.5405830336578483,
          "z": 29.49026621072846
        },
        {
          "x": 2.3724648510758555,
          "z": 34.31725416802062
        },
        {
          "x": -0.23862285116624352,
          "z": 39.916560198479544
        },
        {
          "x": -2.5061463820607015,
          "z": 44.260849360042485
        },
        {
          "x": -4.567531410146568,
          "z": 47.25358189356364
        },
        {
          "x": -6.972480609580075,
          "z": 51.40479153683489
        }
      ]
    },
    {
      "k": 18,
      "height_ft": 4.5,
      "points_xz_ft": [
        {
          "x": 24.29185898305557,
          "z": 9.79615534497642
        },
        {
          "x": 21.749484115082996,
          "z": 13.56120595166431
        },
        {
          "x": 18.932257910032316,
          "z": 16.360858966893765
        },
        {
          "x": 15.427903362286349,
          "z": 19.93283005528998
        },
        {
          "x": 12.679389991505195,
          "z": 22.829022829665266
        },
        {
          "x": 9.930876620724039,
          "z": 25.918295122332257
        },
        {
          "x": 7.044937581403813,
          "z": 29.297186692436778
        },
        {
          "x": 5.5332552274741795,
          "z": 33.73801561314556
        },
        {
          "x": 3.678008702196905,
          "z": 37.88922525641682
        },
        {
          "x": 1.547910839841503,
          "z": 43.295451768584044
        },
        {
          "x": -0.6508998567834123,
          "z": 47.446661411855324
        },
        {
          "x": -2.7809977191388144,
          "z": 50.34285418623061
        },
        {
          "x": -3.9491159017208073,
          "z": 53.62520599718929
        }
      ]
    },
    {
      "k": 19,
      "height_ft": 4.75,
      "points_xz_ft": [
        {
          "x": 24.085720480246984,
          "z": 13.175046915080939
        },
        {
          "x": 21.955622617891596,
          "z": 16.843557762622986
        },
        {
          "x": 18.863545075762786,
          "z": 20.125909573581662
        },
        {
          "x": 16.252457373520688,
          "z": 23.215181866248635
        },
        {
          "x": 13.435231168470004,
          "z": 25.628675844894733
        },
        {
          "x": 11.305133306114618,
          "z": 28.814487896707547
        },
        {
          "x": 9.518599615106856,
          "z": 30.841822838770273
        },
        {
          "x": 7.663353089829581,
          "z": 35.57227103691658
        },
        {
          "x": 6.220383570169475,
          "z": 40.39925899420876
        },
        {
          "x": 4.571275547700785,
          "z": 44.35738911918833
        },
        {
          "x": 2.3724648510758555,
          "z": 48.60513852160543
        },
        {
          "x": 0.9294953314157497,
          "z": 51.11517225939737
        },
        {
          "x": -0.7196126910529405,
          "z": 54.783683106939414
        }
      ]
    },
    {
      "k": 20,
      "height_ft": 5.0,
      "points_xz_ft": [
        {
          "x": 23.742156308899343,
          "z": 16.55393848518546
        },
        {
          "x": 21.474632778004885,
          "z": 19.450131259560745
        },
        {
          "x": 19.688099086997138,
          "z": 21.477466201623454
        },
        {
          "x": 17.42057555610268,
          "z": 24.66327825343629
        },
        {
          "x": 15.290477693747293,
          "z": 28.042169823540807
        },
        {
          "x": 13.022954162852836,
          "z": 29.972965006457674
        },
        {
          "x": 11.579984643192729,
          "z": 34.31725416802062
        },
        {
          "x": 9.862163786454511,
          "z": 39.047702366166945
        },
        {
          "x": 7.938204426907694,
          "z": 43.58507104602159
        },
        {
          "x": 6.08295790163042,
          "z": 47.543201171001165
        },
        {
          "x": 3.884147205005489,
          "z": 51.59787105512658
        },
        {
          "x": 2.5786033538844397,
          "z": 53.81828551548097
        }
      ]
    },
    {
      "k": 21,
      "height_ft": 5.25,
      "points_xz_ft": [
        {
          "x": 22.986315131934518,
          "z": 20.41552885101919
        },
        {
          "x": 20.99364293811819,
          "z": 22.829022829665266
        },
        {
          "x": 19.894237589805723,
          "z": 25.1459770491655
        },
        {
          "x": 17.695426893180795,
          "z": 28.235249341832493
        },
        {
          "x": 16.252457373520688,
          "z": 30.745283079624432
        },
        {
          "x": 14.397210848243413,
          "z": 33.73801561314556
        },
        {
          "x": 13.091666997122363,
          "z": 37.020367424104236
        },
        {
          "x": 11.236420471845088,
          "z": 40.97849754908381
        },
        {
          "x": 10.34315362634121,
          "z": 44.550468637480016
        },
        {
          "x": 6.907511912864757,
          "z": 51.98403009170995
        }
      ]
    },
    {
      "k": 22,
      "height_ft": 5.5,
      "points_xz_ft": [
        {
          "x": 21.131068606657244,
          "z": 26.49753367720731
        },
        {
          "x": 18.38255523587609,
          "z": 29.683345729020147
        },
        {
          "x": 16.527308710598813,
          "z": 33.64147585399972
        },
        {
          "x": 14.809487853860581,
          "z": 36.827287905812554
        },
        {
          "x": 13.229092665661419,
          "z": 41.461196344813025
        },
        {
          "x": 11.098994803306018,
          "z": 48.21897948502206
        }
      ]
    }
  ]
}